{
  "date": "2026-04-28",
  "time": "16:04",
  "mood": "Cautious",
  "sectors": [
    {
      "sector": "auto",
      "direction": "Bearish",
      "conviction": 2,
      "news_driver": "Maruti Suzuki Q4 Results",
      "theme": "null",
      "stocks": [
        {
          "name": "Maruti Suzuki India",
          "ticker": "MARUTI.NS",
          "impact": "Bearish",
          "reason": "Maruti Suzuki's Q4 profit drop -> margin pressure due to high input costs -> negative impact on stock price",
          "quant": "-5% revenue growth in Q1"
        },
        {
          "name": "Tata Motors",
          "ticker": "TATAMOTORS.NS",
          "impact": "Bearish",
          "reason": "Maruti Suzuki's margin pressure -> industry-wide concern on input costs -> potential decline in Tata Motors' stock",
          "quant": "margins -100bps"
        }
      ],
      "watch": "Maruti Suzuki's stock price movement after dividend announcement"
    },
    {
      "sector": "banking",
      "direction": "Neutral",
      "conviction": 1,
      "news_driver": "ECL norms from April 2027",
      "theme": "null",
      "stocks": [
        {
          "name": "State Bank of India",
          "ticker": "SBIN.NS",
          "impact": "Neutral",
          "reason": "ECL norms implementation -> preparedness of Indian banks -> no significant impact on SBI's stock",
          "quant": "null"
        }
      ],
      "watch": "April 2027 ECL norms implementation"
    },
    {
      "sector": "realty",
      "direction": "Bullish",
      "conviction": 2,
      "news_driver": "Bagmane Prime Office REIT IPO",
      "theme": "null",
      "stocks": [
        {
          "name": "DLF",
          "ticker": "DLF.NS",
          "impact": "Bullish",
          "reason": "Bagmane Prime Office REIT IPO -> increased investor interest in real estate -> potential upside in DLF's stock",
          "quant": "+5% revenue growth in Q2"
        }
      ],
      "watch": "Bagmane Prime Office REIT IPO subscription numbers"
    },
    {
      "sector": "energy",
      "direction": "Bullish",
      "conviction": 2,
      "news_driver": "India's power market entering a storage-led transformation phase",
      "theme": "null",
      "stocks": [
        {
          "name": "Tata Power",
          "ticker": "TATAPOWER.NS",
          "impact": "Bullish",
          "reason": "India's power market transformation -> increased demand for energy storage solutions -> potential growth in Tata Power's revenue",
          "quant": "+10% order book growth"
        }
      ],
      "watch": "Government's energy storage policy announcements"
    }
  ],
  "themes": [
    "null"
  ]
}