{
  "date": "2026-07-21",
  "time": "11:39",
  "mood": "Bearish",
  "sectors": [
    {
      "sector": "banking",
      "direction": "Bearish",
      "conviction": 2,
      "news_driver": "Private bank stocks lead losses due to rising crude oil prices",
      "theme": "PSU_rotation",
      "stocks": [
        {
          "name": "ICICI Bank",
          "ticker": "ICICIBANK.NS",
          "impact": "Bearish",
          "reason": "Rising crude oil prices -> increased import costs -> reduced margins for ICICI Bank",
          "quant": "margins -100bps"
        },
        {
          "name": "HDFC Bank",
          "ticker": "HDFCBANK.NS",
          "impact": "Bearish",
          "reason": "Rising crude oil prices -> increased import costs -> reduced consumer spending and loan growth for HDFC Bank",
          "quant": "loan growth -5%"
        },
        {
          "name": "Axis Bank",
          "ticker": "AXISBANK.NS",
          "impact": "Bearish",
          "reason": "Rising crude oil prices -> increased import costs -> reduced margins and increased NPA provisions for Axis Bank",
          "quant": "NPA provisions +10%"
        }
      ],
      "watch": "PSU bank stocks like SBI and PNB for potential rotation"
    },
    {
      "sector": "energy",
      "direction": "Bearish",
      "conviction": 2,
      "news_driver": "Rising crude oil prices",
      "theme": null,
      "stocks": [
        {
          "name": "Reliance Industries",
          "ticker": "RELIANCE.NS",
          "impact": "Bearish",
          "reason": "Rising crude oil prices -> increased refining costs -> reduced margins for Reliance Industries",
          "quant": "refining margins -150bps"
        }
      ],
      "watch": "Brent crude oil price levels"
    },
    {
      "sector": "fmcg",
      "direction": "Neutral",
      "conviction": 1,
      "news_driver": "No specific news",
      "theme": null,
      "stocks": [
        {
          "name": "Colgate Palmolive (India)",
          "ticker": "COLPAL.NS",
          "impact": "Neutral",
          "reason": "No specific news -> no change in business fundamentals -> neutral impact on Colgate Palmolive",
          "quant": null
        }
      ],
      "watch": "Q2 earnings release"
    },
    {
      "sector": "psu",
      "direction": "Bullish",
      "conviction": 1,
      "news_driver": "PNB shares jump 7% in 2 days after Q1 earnings",
      "theme": "PSU_rotation",
      "stocks": [
        {
          "name": "Punjab National Bank",
          "ticker": "PNB.NS",
          "impact": "Bullish",
          "reason": "Q1 earnings beat -> improved business fundamentals -> increased investor confidence in PNB",
          "quant": "revenue +5%"
        }
      ],
      "watch": "PSU bank stocks for potential rotation"
    }
  ],
  "themes": [
    "PSU_rotation"
  ]
}