{
  "date": "2026-06-03",
  "time": "19:55",
  "mood": "Cautious",
  "sectors": [
    {
      "sector": "banking",
      "direction": "Neutral",
      "conviction": 2,
      "news_driver": "RBI's rate-setting panel starts deliberations",
      "theme": "null",
      "stocks": [
        {
          "name": "HDFC Bank",
          "ticker": "HDFCBANK.NS",
          "impact": "Neutral",
          "reason": "RBI's potential pause in rate hikes -> reduced borrowing costs -> neutral impact on HDFC Bank's NIM",
          "quant": "NIM -20bps"
        },
        {
          "name": "ICICI Bank",
          "ticker": "ICICIBANK.NS",
          "impact": "Neutral",
          "reason": "RBI's potential pause in rate hikes -> reduced lending rates -> neutral impact on ICICI Bank's loan growth",
          "quant": "loan growth +5-7% Q2"
        }
      ],
      "watch": "RBI policy announcement on Friday"
    },
    {
      "sector": "auto",
      "direction": "Bullish",
      "conviction": 2,
      "news_driver": "Tata Motors to use Chery-made platform for Avinya EVs",
      "theme": "null",
      "stocks": [
        {
          "name": "Tata Motors",
          "ticker": "TATAMOTORS.NS",
          "impact": "Bullish",
          "reason": "Tata Motors' partnership with Chery -> reduced EV development costs -> increased competitiveness for Tata Motors",
          "quant": "EV sales +15% Q3"
        }
      ],
      "watch": "Tata Motors' Q2 earnings"
    },
    {
      "sector": "oil_gas",
      "direction": "Bullish",
      "conviction": 2,
      "news_driver": "Cabinet approves \u20b910,000 crore ATF price stabilisation fund",
      "theme": "null",
      "stocks": [
        {
          "name": "Indian Oil Corporation",
          "ticker": "IOC.NS",
          "impact": "Bullish",
          "reason": "Government's ATF price stabilisation fund -> reduced jet fuel prices -> increased margins for Indian Oil Corporation",
          "quant": "margins +100bps"
        }
      ],
      "watch": "ATF price movement"
    }
  ],
  "themes": [
    "null"
  ]
}